LICENSE
MANIFEST.in
README
setup.py
ckeditor/__init__.py
ckeditor/fields.py
ckeditor/models.py
ckeditor/static/ckeditor/ckeditor.css
ckeditor/static/ckeditor/ckeditor.js
ckeditor/static/ckeditor/config.js
ckeditor/static/ckeditor/contents.css
ckeditor/static/ckeditor/adapters/jquery.js
ckeditor/static/ckeditor/images/spacer.gif
ckeditor/static/ckeditor/lang/_languages.js
ckeditor/static/ckeditor/lang/_translationstatus.txt
ckeditor/static/ckeditor/lang/af.js
ckeditor/static/ckeditor/lang/ar.js
ckeditor/static/ckeditor/lang/bg.js
ckeditor/static/ckeditor/lang/bn.js
ckeditor/static/ckeditor/lang/bs.js
ckeditor/static/ckeditor/lang/ca.js
ckeditor/static/ckeditor/lang/cs.js
ckeditor/static/ckeditor/lang/cy.js
ckeditor/static/ckeditor/lang/da.js
ckeditor/static/ckeditor/lang/de.js
ckeditor/static/ckeditor/lang/el.js
ckeditor/static/ckeditor/lang/en-au.js
ckeditor/static/ckeditor/lang/en-ca.js
ckeditor/static/ckeditor/lang/en-gb.js
ckeditor/static/ckeditor/lang/en.js
ckeditor/static/ckeditor/lang/eo.js
ckeditor/static/ckeditor/lang/es.js
ckeditor/static/ckeditor/lang/et.js
ckeditor/static/ckeditor/lang/eu.js
ckeditor/static/ckeditor/lang/fa.js
ckeditor/static/ckeditor/lang/fi.js
ckeditor/static/ckeditor/lang/fo.js
ckeditor/static/ckeditor/lang/fr-ca.js
ckeditor/static/ckeditor/lang/fr.js
ckeditor/static/ckeditor/lang/gl.js
ckeditor/static/ckeditor/lang/gu.js
ckeditor/static/ckeditor/lang/he.js
ckeditor/static/ckeditor/lang/hi.js
ckeditor/static/ckeditor/lang/hr.js
ckeditor/static/ckeditor/lang/hu.js
ckeditor/static/ckeditor/lang/is.js
ckeditor/static/ckeditor/lang/it.js
ckeditor/static/ckeditor/lang/ja.js
ckeditor/static/ckeditor/lang/km.js
ckeditor/static/ckeditor/lang/ko.js
ckeditor/static/ckeditor/lang/lt.js
ckeditor/static/ckeditor/lang/lv.js
ckeditor/static/ckeditor/lang/mn.js
ckeditor/static/ckeditor/lang/ms.js
ckeditor/static/ckeditor/lang/nb.js
ckeditor/static/ckeditor/lang/nl.js
ckeditor/static/ckeditor/lang/no.js
ckeditor/static/ckeditor/lang/pl.js
django_admin_ckeditor.egg-info/PKG-INFO
django_admin_ckeditor.egg-info/SOURCES.txt
django_admin_ckeditor.egg-info/dependency_links.txt
django_admin_ckeditor.egg-info/not-zip-safe
django_admin_ckeditor.egg-info/requires.txt
django_admin_ckeditor.egg-info/top_level.txt