Metadata-Version: 1.0
Name: django-admin-ckeditor
Version: 0.0.1
Summary: Ckeditor integration with Django admin.
Home-page: https://github.com/madisona/django-admin-ckeditor
Author: Aaron Madison
Author-email: UNKNOWN
License: UNKNOWN
Platform: UNKNOWN
Classifier: Development Status :: 4 - Beta
Classifier: Environment :: Web Environment
Classifier: Framework :: Django
Classifier: Intended Audience :: Developers
Classifier: License :: OSI Approved :: BSD License
Classifier: Operating System :: OS Independent
Classifier: Programming Language :: Python
Classifier: Topic :: Software Development
Classifier: Topic :: Software Development :: Libraries :: Application Frameworks
